[
  {
    "id": "1775196683144",
    "ts": "1775196683144",
    "title": "[MY LINKS] - Vos retours et suggestions",
    "body": "Salut a tous,\n\nComme vous le savez, MY LINKS est notre terminal communautaire Star Citizen — guides operationnels, timer pyam, guides events, et plus encore.\nLe site evolue en permanence et j'ai besoin de vos retours pour l'ameliorer !\n\nCe que vous pouvez signaler :\nBugs ou comportements inattendus\nIdees de nouvelles fonctionnalites\nGuides ou images manquants\nLiens utiles a ajouter\nEvenements SC a referencer\n\nComment participer :\nPostez directement dans le fil : DISCORD / sujet-sc / [MY LINKS] — Vos retours & suggestions, avec vos suggestions.\nSoyez precis — une bonne description = une correction rapide.\n\nLes suggestions recueillies seront reprises et discutees lors de nos reunions.\n\nMerci a tous pour votre soutien — c'est une ressource construite pour notre commu, par la commu.\n\n— Slowed",
    "pinned": false,
    "author": "slowed3821",
    "authorId": "282466483177521152"
  },
  {
    "id": "1774441030611",
    "ts": "1774441030611",
    "title": "Ouverture d'un canal de communication",
    "body": "Hello 404",
    "pinned": false,
    "author": "slowed3821",
    "authorId": "282466483177521152"
  }
]